apyhgnc/__init__.py
apyhgnc/apyhgnc.py
apyhgnc/classes.py
apyhgnc-0.2.6.dist-info/AUTHORS.rst
apyhgnc-0.2.6.dist-info/LICENSE
apyhgnc-0.2.6.dist-info/METADATA
apyhgnc-0.2.6.dist-info/WHEEL
apyhgnc-0.2.6.dist-info/top_level.txt
apyhgnc-0.2.6.dist-info/RECORD
