Metadata-Version: 2.1
Name: apyhgnc
Version: 0.2.6
Summary: Async pythonic interface to HGNC.
Home-page: https://github.com/robertopreste/apyhgnc
Author: Roberto Preste
Author-email: robertopreste@gmail.com
License: MIT license
Keywords: apyhgnc
Platform: UNKNOWN
Classifier: Development Status :: 2 - Pre-Alpha
Classifier: Intended Audience :: Developers
Classifier: License :: OSI Approved :: MIT License
Classifier: Natural Language :: English
Classifier: Programming Language :: Python :: 3
Classifier: Programming Language :: Python :: 3.5
Classifier: Programming Language :: Python :: 3.6
Classifier: Programming Language :: Python :: 3.7
Requires-Dist: requests (>=2.21)
Requires-Dist: pandas (>=0.24.2)
Requires-Dist: asyncio (>=3.4.3)
Requires-Dist: aiohttp (>=3.5.4)
